[{"opinion_id": "11629988", "author": "Hubert", "recomendation": "Polecam", "stars": "5/5", "content": "Œwietnie wykonane. Obawia³em siê bia³ego koloru ale jest on w odcieniu per³owym a same s³uchawki s¹ delikatnie opalizuj¹ce i miejscami jasno szaro co wygl¹da bardzo ³adnie. Jeszcze nigdy mi siê nie roz³adowa³y ale s³ucham nie d³u¿ej ni¿ 2h w jednej sesji. DŸwiêk bardzo dobry, mikrofon tak¿e. Nikt nie narzeka³ na jakoœæ po³¹czenia. Jedyne do czego mo¿na siê przyczepiæ to, ¿e z pude³ka s³uchawki mo¿na w ca³oœci na³adowaæ tylko 1 raz.", "pros": null, "cons": null, "useful": "0", "useless": "1", "purchased": null, "purchase_date": "2020-01-06 15:25:36", "review_date": "2020-01-23 13:15:09"}, {"opinion_id": "10356484", "author": "Marek", "recomendation": "Polecam", "stars": "5/5", "content": "ok", "pros": "wygl¹d\nwygoda u¿ywania", "cons": "jakoœæ dŸwiêku", "useful": "0", "useless": "11", "purchased": null, "purchase_date": "2019-03-30 17:25:34", "review_date": "2019-04-05 15:22:41"}, {"opinion_id": "10469786", "author": "A...k", "recomendation": "Polecam", "stars": "5/5", "content": "Jakby co to samsung ju¿ kilka lat temu przejê³o akg i jbl, wiêc to jest zagranie wy³¹cznie marketingowe", "pros": "asystent google\nd³ugi czas dzia³ania\njakoœæ dŸwiêku\nrewelacyjna jakoœæ rozmów\nwygl¹d\nwygoda u¿ywania", "cons": null, "useful": "14", "useless": "3", "purchased": null, "purchase_date": "2019-09-23 20:32:50", "review_date": "2019-05-02 12:14:56"}, {"opinion_id": "10755668", "author": "Adam", "recomendation": "Polecam", "stars": "4,5/5", "content": "Jak dla mnie za ciche ale moja kobieta mówi ¿e to dobrze bo i tak ju¿ g³uchy jestem, tak wiêc chyba zostan¹ na d³u¿ej.", "pros": null, "cons": null, "useful": "8", "useless": "2", "purchased": null, "purchase_date": "2019-06-27 21:20:26", "review_date": "2019-07-08 12:41:28"}, {"opinion_id": "10744319", "author": "Dawid", "recomendation": "Polecam", "stars": "4/5", "content": "Mam od kilku dni i naprawdê fajne, zaskoczy³a mnie jakoœæ rozmów telefonicznych na czym mi zalezalo", "pros": "asystent google\nd³ugi czas dzia³ania\ndobrze siê trzymaj¹ w uchu\ngenialny bass\njakoœæ dŸwiêku\nrewelacyjna jakoœæ rozmów\nwygl¹d", "cons": "trochê niewygodne na d³u¿ej w uszach\nwygoda u¿ywania", "useful": "0", "useless": "0", "purchased": null, "purchase_date": null, "review_date": "2019-07-04 21:09:30"}, {"opinion_id": "11250795", "author": "Jakub", "recomendation": "Polecam", "stars": "5/5", "content": "s³uchawki spe³niaj¹ moje oczekiwania, choæ mog³y by byæ trochê g³oœniejsze,", "pros": "genialny bass\njakoœæ dŸwiêku\nrewelacyjna jakoœæ rozmów\nwygl¹d\nwygoda u¿ywania", "cons": null, "useful": "0", "useless": "0", "purchased": null, "purchase_date": "2019-10-08 07:17:51", "review_date": "2019-11-08 06:51:33"}, {"opinion_id": "10776553", "author": "Grzegorz", "recomendation": "Polecam", "stars": "4,5/5", "content": "Mog³yby byæ tañsze poza tym nie ma siê do czego przyczepiæ", "pros": "asystent google\njakoœæ dŸwiêku\nrewelacyjna jakoœæ rozmów\nwygl¹d", "cons": null, "useful": "0", "useless": "0", "purchased": null, "purchase_date": "2019-07-03 13:55:39", "review_date": "2019-07-12 11:24:43"}, {"opinion_id": "11435783", "author": "Zgrzewacz", "recomendation": "Polecam", "stars": "5/5", "content": "S³uchawki s¹ zaskakuj¹co dobre, jestem bardzo zadowolony", "pros": "asystent google\ngenialny bass\njakoœæ dŸwiêku\nrewelacyjna jakoœæ rozmów\nwygl¹d\nwygoda u¿ywania", "cons": "trochê niewygodne na d³u¿ej w uszach", "useful": "0", "useless": "0", "purchased": null, "purchase_date": "2019-12-11 13:55:54", "review_date": "2019-12-16 11:05:21"}, {"opinion_id": "11741510", "author": "U¿ytkownik Ceneo", "recomendation": "Polecam", "stars": "4,5/5", "content": "Jaes ok ale moglo by byc lepiej z dzwiekin.t", "pros": null, "cons": null, "useful": "0", "useless": "1", "purchased": null, "purchase_date": "2020-02-11 09:01:59", "review_date": "2020-02-13 22:09:55"}, {"opinion_id": "11527316", "author": "Jerzy", "recomendation": "Polecam", "stars": "5/5", "content": "Super produkt jestem zadowolony .", "pros": null, "cons": null, "useful": "0", "useless": "0", "purchased": null, "purchase_date": "2019-12-30 12:08:38", "review_date": "2020-01-03 16:21:47"}, {"opinion_id": "11523899", "author": "Piotr", "recomendation": "Polecam", "stars": "5/5", "content": "O dziwo trzymaj¹ siê ucha.", "pros": null, "cons": null, "useful": "0", "useless": "0", "purchased": null, "purchase_date": "2019-12-27 14:13:05", "review_date": "2020-01-03 06:42:51"}, {"opinion_id": "11644355", "author": "U¿ytkownik Ceneo", "recomendation": "Polecam", "stars": "5/5", "content": "Produkt zgodny z opisem", "pros": null, "cons": null, "useful": "0", "useless": "0", "purchased": null, "purchase_date": "2019-12-26 21:20:23", "review_date": "2020-01-26 21:59:39"}, {"opinion_id": "11462389", "author": "k", "recomendation": "Polecam", "stars": "5/5", "content": "polecam", "pros": "genialny bass\njakoœæ dŸwiêku\nrewelacyjna jakoœæ rozmów\nwygl¹d\nwygoda u¿ywania", "cons": null, "useful": "0", "useless": "0", "purchased": null, "purchase_date": "2019-12-16 15:33:46", "review_date": "2019-12-20 11:08:14"}, {"opinion_id": "11032569", "author": "Jacek", "recomendation": "Polecam", "stars": "5/5", "content": "S³uchawki prawie niewa¿kie. Jakoœæ dŸwiêku bardzo dobra. Jednak najwiêksz¹ zalet¹ jest ergonomia i sposób dzia³ania. Nareszcie mo¿na korzystaæ z nich praktycznie wszêdzie i bardzo szybko. Zak³adasz na uszy i wszystko siê samo konfiguruje. Obs³uga gestów- Super. Polecam gor¹co. M¹drze wydane pieni¹dze.", "pros": null, "cons": null, "useful": "2", "useless": "0", "purchased": null, "purchase_date": "2019-09-10 14:24:47", "review_date": "2019-09-12 11:06:02"}, {"opinion_id": "10359456", "author": "Dasik", "recomendation": "Polecam", "stars": "5/5", "content": "Kocham te s³uchawki! S¹ to moje pierwsze s³uchawki bezprzewodowe i wiem, ¿e ju¿ nigdy nie wrócê do s³uchawek przewodowych. Genialn¹ rzecz¹ w tych s³uchawkach jest tak¿e zasiêg, który wynosi ponad 10 m. Polecam!", "pros": "genialny bass\njakoœæ dŸwiêku\nwygl¹d\nwygoda u¿ywania", "cons": null, "useful": "4", "useless": "0", "purchased": null, "purchase_date": null, "review_date": "2019-04-06 12:21:08"}, {"opinion_id": "10310577", "author": "Marcin", "recomendation": "Polecam", "stars": "5/5", "content": "dlaczego w opisie piszesz ze sa super extra, \"Dziêki czysty, wyraŸny, bez szumów i opóŸnieñ\" a ponizej jakosc dzwieku jest wymieniona jakos wada?", "pros": "wygl¹d\nwygoda u¿ywania", "cons": "jakoœæ dŸwiêku", "useful": "0", "useless": "10", "purchased": null, "purchase_date": "2019-04-15 15:05:06", "review_date": "2019-03-28 00:31:38"}, {"opinion_id": "10524813", "author": "Marcel^^", "recomendation": "Polecam", "stars": "5/5", "content": "Super s³uchawki! To moje pierwsze bezprzewodowe. Znalaz³em je przez przypadek na gsm24.pl i uzna³em ¿e mo¿e warto pójœæ \"za duchem czasu\" i totalnie nie ¿a³ujê! Ju¿ nie wrócê do tych na kabelku. Polecam!", "pros": null, "cons": null, "useful": "0", "useless": "0", "purchased": null, "purchase_date": null, "review_date": "2019-05-15 10:45:44"}, {"opinion_id": "11445261", "author": "Rafa³", "recomendation": "Polecam", "stars": "5/5", "content": "Wczeœniej mia³em Creativy ale nie by³em zachwycony. Sprzeda³em i kupi³em te. S¹ mega. Wygodne, ³adnie graj¹, ³adowanie indukcyjne no i z moim Samsungiem S9+ œwietnie wspó³pracuj¹. Drogie ale warto.", "pros": null, "cons": null, "useful": "0", "useless": "0", "purchased": null, "purchase_date": "2019-12-11 14:05:09", "review_date": "2019-12-17 16:29:30"}, {"opinion_id": "10955064", "author": "U¿ytkownik Ceneo", "recomendation": "Polecam", "stars": "4/5", "content": "Jakoœæ dŸwiêku nie jest fenomenalna, niemniej s³uchawki œwietnie œwietnie spisuj¹ siê na si³owni czy podczas biegania. S¹ wygodne i dobrze trzymaj¹ siê w uchu.", "pros": "asystent google\nd³ugi czas dzia³ania\ndobrze siê trzymaj¹ w uchu\ngenialny bass\nrewelacyjna jakoœæ rozmów\nwygl¹d", "cons": "jakoœæ dŸwiêku\ntrochê niewygodne na d³u¿ej w uszach", "useful": "0", "useless": "6", "purchased": null, "purchase_date": "2019-08-17 23:06:43", "review_date": "2019-08-23 10:34:52"}, {"opinion_id": "11581951", "author": "Kapikap", "recomendation": "Polecam", "stars": "5/5", "content": "bardzo polecam bardzo dobra jakoœæ dziwiêku wygl¹d te¿ fajny jedyne ¿eczy jakie nie porywaj¹ to mog³y ³u¿ej na jednym ³adowaniu wytrzymaæ i gdyby uszy nie bola³y po d³u¿szym czasie", "pros": "asystent google\nd³ugi czas dzia³ania\ndobrze siê trzymaj¹ w uchu\ngenialny bass\njakoœæ dŸwiêku\nrewelacyjna jakoœæ rozmów\nwygl¹d\nwygoda u¿ywania", "cons": "trochê niewygodne na d³u¿ej w uszach", "useful": "0", "useless": "0", "purchased": null, "purchase_date": null, "review_date": "2020-01-14 16:23:47"}, {"opinion_id": "11783401", "author": "U¿ytkownik Ceneo", "recomendation": "Polecam", "stars": "4/5", "content": "Jakoœæ okej, obs³uga okej, trzymanie w uchu okej. Lekki minus jedynie za dŸwiêk - trochê za ciche jak dla mnie.", "pros": null, "cons": null, "useful": "0", "useless": "0", "purchased": null, "purchase_date": "2020-02-18 18:49:16", "review_date": "2020-02-21 11:52:19"}, {"opinion_id": "10698213", "author": "Ania<3", "recomendation": "Polecam", "stars": "5/5", "content": "Kupowa³em telefon na gsm24.pl i dokupi³em je , to moje pierwsze bezprzewodowe s³uchawki i nie zawiod³em siê !", "pros": null, "cons": null, "useful": "0", "useless": "0", "purchased": null, "purchase_date": null, "review_date": "2019-06-25 08:28:59"}, {"opinion_id": "11630878", "author": "U¿ytkownik Ceneo", "recomendation": "Polecam", "stars": "5/5", "content": "Bardzo dobre wykonanie, dŸwiêk jest mega, dobre basy które mo¿na wzmocniæ, du¿o ciekawych opcji. Polecam", "pros": null, "cons": null, "useful": "0", "useless": "0", "purchased": null, "purchase_date": "2020-01-19 15:46:06", "review_date": "2020-01-23 15:31:21"}, {"opinion_id": "10916213", "author": "Piorek", "recomendation": "Polecam", "stars": "5/5", "content": "S³uchawki œwietne, bardzo dobrze siê trzymaj¹.\r\nJakoœ dŸwiêku bez za¿aleñ.", "pros": "asystent google\nd³ugi czas dzia³ania\ndobrze siê trzymaj¹ w uchu\ngenialny bass\njakoœæ dŸwiêku\nrewelacyjna jakoœæ rozmów\nwygl¹d\nwygoda u¿ywania", "cons": null, "useful": "1", "useless": "0", "purchased": null, "purchase_date": "2019-08-10 12:38:49", "review_date": "2019-08-14 11:14:45"}, {"opinion_id": "11591392", "author": "Krystyna", "recomendation": "Polecam", "stars": "5/5", "content": "S³uchaweczki rewelacja, sprawdzaj¹ siê, podczas biegu idealne.", "pros": null, "cons": null, "useful": "0", "useless": "0", "purchased": null, "purchase_date": "2019-12-09 19:45:43", "review_date": "2020-01-16 09:49:46"}, {"opinion_id": "11282012", "author": "Adam", "recomendation": "Polecam", "stars": "5/5", "content": "W dniu dzisiejszym odebra³em . Narazie nie mam zdania.", "pros": null, "cons": null, "useful": "1", "useless": "0", "purchased": null, "purchase_date": "2019-11-08 15:57:40", "review_date": "2019-11-15 19:18:26"}, {"opinion_id": "11656651", "author": "U¿ytkownik Ceneo", "recomendation": "Polecam", "stars": "5/5", "content": "Polecam dzia³aj¹ œwietnie jakoœæ wykonania super", "pros": null, "cons": null, "useful": "0", "useless": "0", "purchased": null, "purchase_date": "2019-12-29 09:04:06", "review_date": "2020-01-29 06:55:28"}, {"opinion_id": "11658306", "author": "U¿ytkownik Ceneo", "recomendation": "Polecam", "stars": "5/5", "content": "Najlepszy obecnue tego typu produkt na rynku", "pros": null, "cons": null, "useful": "0", "useless": "0", "purchased": null, "purchase_date": "2020-01-24 10:49:31", "review_date": "2020-01-29 11:42:08"}, {"opinion_id": "11538567", "author": "stoper", "recomendation": "Polecam", "stars": "5/5", "content": "Bardzo wygodne.Œwietna jakoœæ dŸwiêku.", "pros": "genialny bass\njakoœæ dŸwiêku\nrewelacyjna jakoœæ rozmów\nwygl¹d\nwygoda u¿ywania", "cons": null, "useful": "0", "useless": "0", "purchased": null, "purchase_date": "2019-12-01 19:46:47", "review_date": "2020-01-06 14:31:37"}, {"opinion_id": "11827503", "author": "U¿ytkownik Ceneo", "recomendation": "Nie polecam", "stars": "0,5/5", "content": "brak by³o kabelka - nadal siê nie mogê doprosiæ", "pros": null, "cons": null, "useful": "0", "useless": "0", "purchased": null, "purchase_date": "2020-01-29 20:19:26", "review_date": "2020-02-29 15:53:40"}, {"opinion_id": "11376290", "author": "Maciej", "recomendation": "Polecam", "stars": "5/5", "content": "Funkcjonalne i wygodne. DŸwiêk super.", "pros": null, "cons": null, "useful": "0", "useless": "0", "purchased": null, "purchase_date": "2019-11-29 16:23:26", "review_date": "2019-12-05 16:30:03"}, {"opinion_id": "11472054", "author": "Grzegorz", "recomendation": "Polecam", "stars": "5/5", "content": "Super produkt w rozs¹dnej cenie", "pros": "d³ugi czas dzia³ania\ndobrze siê trzymaj¹ w uchu\ngenialny bass\nrewelacyjna jakoœæ rozmów\ntrochê niewygodne na d³u¿ej w uszach\nwygl¹d\nwygoda u¿ywania", "cons": null, "useful": "0", "useless": "0", "purchased": null, "purchase_date": "2019-11-21 20:11:09", "review_date": "2019-12-22 14:13:06"}, {"opinion_id": "11762082", "author": "U¿ytkownik Ceneo", "recomendation": "Polecam", "stars": "5/5", "content": "S³uchawki sprawuj¹ siê œwietnie", "pros": null, "cons": null, "useful": "0", "useless": "0", "purchased": null, "purchase_date": "2020-02-13 08:15:53", "review_date": "2020-02-18 11:30:53"}, {"opinion_id": "11643534", "author": "U¿ytkownik Ceneo", "recomendation": "Polecam", "stars": "5/5", "content": "³adne, praktyczne, super jakoœæ", "pros": null, "cons": null, "useful": "0", "useless": "0", "purchased": null, "purchase_date": "2020-01-08 15:04:30", "review_date": "2020-01-26 16:04:39"}, {"opinion_id": "11551131", "author": "Iwona", "recomendation": "Polecam", "stars": "5/5", "content": "Towar spe³nia moje oczekiwania", "pros": "asystent google\nd³ugi czas dzia³ania\ndobrze siê trzymaj¹ w uchu\ngenialny bass\njakoœæ dŸwiêku\nrewelacyjna jakoœæ rozmów\nwygl¹d\nwygoda u¿ywania", "cons": null, "useful": "0", "useless": "0", "purchased": null, "purchase_date": "2020-01-02 15:39:59", "review_date": "2020-01-08 17:23:51"}, {"opinion_id": "11163741", "author": "iwona", "recomendation": "Polecam", "stars": "5/5", "content": "produkt zgodny z oczekiwaniami.", "pros": "jakoœæ dŸwiêku\nrewelacyjna jakoœæ rozmów\nwygl¹d\nwygoda u¿ywania", "cons": null, "useful": "0", "useless": "0", "purchased": null, "purchase_date": "2019-10-12 12:58:25", "review_date": "2019-10-16 19:10:47"}, {"opinion_id": "11817020", "author": "U¿ytkownik Ceneo", "recomendation": "Polecam", "stars": "5/5", "content": "Spe³niaj¹ moje oczekiwania", "pros": null, "cons": null, "useful": "0", "useless": "0", "purchased": null, "purchase_date": "2020-02-17 12:03:48", "review_date": "2020-02-27 19:30:18"}, {"opinion_id": "11677292", "author": "U¿ytkownik Ceneo", "recomendation": "Polecam", "stars": "5/5", "content": "SWIETNY PRODUKT,  POLECAM", "pros": null, "cons": null, "useful": "0", "useless": "0", "purchased": null, "purchase_date": "2019-12-18 11:16:57", "review_date": "2020-02-01 00:10:15"}, {"opinion_id": "11893433", "author": "U¿ytkownik Ceneo", "recomendation": "Polecam", "stars": "5/5", "content": "Spe³nia moje wymagania", "pros": null, "cons": null, "useful": "0", "useless": "0", "purchased": null, "purchase_date": "2020-03-09 17:40:26", "review_date": "2020-03-12 11:46:34"}, {"opinion_id": "11023225", "author": "Marian", "recomendation": "Polecam", "stars": "4/5", "content": "jest zgodny z opisem.", "pros": null, "cons": null, "useful": "0", "useless": "0", "purchased": null, "purchase_date": "2019-08-11 22:11:03", "review_date": "2019-09-10 08:15:22"}, {"opinion_id": "11744391", "author": "U¿ytkownik Ceneo", "recomendation": "Polecam", "stars": "5/5", "content": "Jestem zadowolona", "pros": null, "cons": null, "useful": "0", "useless": "0", "purchased": null, "purchase_date": "2020-02-10 20:38:20", "review_date": "2020-02-14 11:32:33"}, {"opinion_id": "11385106", "author": "Anio³ek", "recomendation": "Polecam", "stars": "5/5", "content": "dobry sprzêcior", "pros": null, "cons": null, "useful": "0", "useless": "0", "purchased": null, "purchase_date": "2019-11-14 10:10:59", "review_date": "2019-12-06 21:50:33"}, {"opinion_id": "11685418", "author": "U¿ytkownik Ceneo", "recomendation": "Polecam", "stars": "5/5", "content": "Nie widzê wad", "pros": null, "cons": null, "useful": "0", "useless": "0", "purchased": null, "purchase_date": "2020-01-27 15:54:15", "review_date": "2020-02-03 16:59:56"}, {"opinion_id": "11725431", "author": "U¿ytkownik Ceneo", "recomendation": "Polecam", "stars": "4,5/5", "content": "Jest ok.", "pros": null, "cons": null, "useful": "0", "useless": "0", "purchased": null, "purchase_date": "2020-01-23 13:56:07", "review_date": "2020-02-11 14:08:33"}, {"opinion_id": "11914834", "author": "U¿ytkownik Ceneo", "recomendation": "Polecam", "stars": "5/5", "content": "polecam", "pros": null, "cons": null, "useful": "0", "useless": "0", "purchased": null, "purchase_date": "2020-03-11 14:09:43", "review_date": "2020-03-16 10:39:25"}, {"opinion_id": "11188099", "author": "K...s", "recomendation": "Polecam", "stars": "5/5", "content": "Polecam", "pros": null, "cons": null, "useful": "0", "useless": "0", "purchased": null, "purchase_date": "2019-09-22 12:31:00", "review_date": "2019-10-23 10:53:29"}, {"opinion_id": "10868937", "author": "Baks", "recomendation": "Polecam", "stars": "4,5/5", "content": "Znalaz³em je na gsm24.pl Zastanawia³o mnie czy nie zgubiê przypadkiem s³uchawki lecz trzymaj¹ siê tak jak trzeba", "pros": "jakoœæ dŸwiêku\nwygl¹d", "cons": null, "useful": "0", "useless": "0", "purchased": null, "purchase_date": null, "review_date": "2019-08-02 14:16:33"}, {"opinion_id": "11937628", "author": "U¿ytkownik Ceneo", "recomendation": "Polecam", "stars": "5/5", "content": "Ok", "pros": null, "cons": null, "useful": "0", "useless": "0", "purchased": null, "purchase_date": "2020-03-05 18:38:45", "review_date": "2020-03-19 07:34:34"}, {"opinion_id": "11931321", "author": "U¿ytkownik Ceneo", "recomendation": "Polecam", "stars": "4,5/5", "content": "..", "pros": null, "cons": null, "useful": "0", "useless": "0", "purchased": null, "purchase_date": "2020-03-04 18:47:34", "review_date": "2020-03-18 14:43:45"}, {"opinion_id": "11856404", "author": "U¿ytkownik Ceneo", "recomendation": "Polecam", "stars": "4/5", "content": "Ok", "pros": null, "cons": null, "useful": "0", "useless": "0", "purchased": null, "purchase_date": "2020-02-24 14:06:59", "review_date": "2020-03-05 20:06:39"}, {"opinion_id": "11407362", "author": "A...7", "recomendation": "Polecam", "stars": "5/5", "content": "Ok", "pros": "jakoœæ dŸwiêku", "cons": null, "useful": "0", "useless": "0", "purchased": null, "purchase_date": "2019-12-01 10:02:44", "review_date": "2019-12-11 15:13:27"}, {"opinion_id": "10794305", "author": "U¿ytkownik Ceneo", "recomendation": "Polecam", "stars": "5/5", "content": "S¹ zar¹biste chocia¿ drogie", "pros": "d³ugi czas dzia³ania\ngenialny bass\njakoœæ dŸwiêku\nrewelacyjna jakoœæ rozmów\nwygl¹d\nwygoda u¿ywania", "cons": null, "useful": "0", "useless": "0", "purchased": null, "purchase_date": null, "review_date": "2019-07-16 22:41:51"}]